bringg_sdk/__init__.py
bringg_sdk/client.py
bringg_sdk/exceptions.py
bringg_sdk/models.py
bringg_sdk/request_factory.py
bringg_sdk/responses.py
bringg_sdk-1.0.1.dist-info/METADATA
bringg_sdk-1.0.1.dist-info/WHEEL
bringg_sdk-1.0.1.dist-info/top_level.txt
bringg_sdk-1.0.1.dist-info/RECORD
