Metadata-Version: 2.1
Name: bringg-sdk
Version: 1.0.1
Requires-Dist: requests
